python_boilerplate_template
