Metadata-Version: 1.1
Name: python-boilerplate-template
Version: 1.0.1
Summary: PasteScript template for initializing a new buildout/pytest/travis/setuptools-enabled Python project
Home-page: http://kt.era.ee/
Author: Konstantin Tretyakov
Author-email: kt@ut.ee
License: MIT
Keywords: pastescript template package
Platform: UNKNOWN
Classifier: Development Status :: 4 - Beta
Classifier: Programming Language :: Python
Classifier: Framework :: Paste
Classifier: Intended Audience :: Developers
Classifier: License :: OSI Approved :: MIT License
Classifier: Topic :: Software Development
Classifier: Environment :: Plugins
